Transformer_Text_AutoEncoder/AutoEncoder.py
Transformer_Text_AutoEncoder/__init__.py
Transformer_Text_AutoEncoder-0.0.4.dist-info/LICENSE
Transformer_Text_AutoEncoder-0.0.4.dist-info/METADATA
Transformer_Text_AutoEncoder-0.0.4.dist-info/WHEEL
Transformer_Text_AutoEncoder-0.0.4.dist-info/top_level.txt
Transformer_Text_AutoEncoder-0.0.4.dist-info/RECORD
