Metadata-Version: 2.1
Name: Transformer-Text-AutoEncoder
Version: 0.0.4
Summary: Transformer Text AutoEncoder: An autoencoder is a type of artificial neural network used to learn efficient encodings of unlabeled data, the same is employed for textual data employing pre-trained models from the hugging-face library.
Home-page: https://github.com/AmanPriyanshu/Transformer-Text-AutoEncoder
Author: Aman Priyanshu
Author-email: amanpriyanshusms2001@gmail.com
License: BSD 2-clause
Classifier: Development Status :: 1 - Planning
Classifier: Intended Audience :: Science/Research
Classifier: License :: OSI Approved :: BSD License
Classifier: Operating System :: POSIX :: Linux
Classifier: Operating System :: Microsoft :: Windows :: Windows 7
Classifier: Operating System :: Microsoft :: Windows :: Windows 8
Classifier: Operating System :: Microsoft :: Windows :: Windows 8.1
Classifier: Operating System :: Microsoft :: Windows :: Windows 10
Classifier: Programming Language :: Python :: 3.6
Classifier: Programming Language :: Python :: 3.7
Classifier: Programming Language :: Python :: 3.8
Classifier: Programming Language :: Python :: 3.9
Classifier: Programming Language :: Python :: 3.10
Classifier: Programming Language :: Python :: 3.11
License-File: LICENSE
Requires-Dist: tqdm (>=4)
Requires-Dist: nltk (>=3)
Requires-Dist: numpy
Requires-Dist: transformers
Requires-Dist: torch
